aos_provisioning/__init__.py
aos_provisioning/main.py
aos_provisioning/onboard/__init__.py
aos_provisioning/onboard/board.py
aos_provisioning/onboard/board_base.py
aos_provisioning/onboard/board_virtual.py
aos_provisioning/onboard/config.py
aos_provisioning/utils/__init__.py
aos_provisioning/utils/cloud_api.py
aos_provisioning/utils/connectors.py
aos_provisioning/utils/errors.py
aos_provisioning/utils/logs.py
aos_provisioning/utils/security.py
aos_provisioning-1.1.2.dist-info/METADATA
aos_provisioning-1.1.2.dist-info/WHEEL
aos_provisioning-1.1.2.dist-info/entry_points.txt
aos_provisioning-1.1.2.dist-info/top_level.txt
aos_provisioning-1.1.2.dist-info/RECORD
