Metadata-Version: 2.1
Name: aos-provisioning
Version: 1.1.2
Summary: Aos provisioning tool
Home-page: UNKNOWN
Author: EPAM Systems
Author-email: support@aoscloud.io
License: Apache License 2.0
Platform: any
Classifier: Operating System :: OS Independent
Classifier: Programming Language :: Python :: 3
Requires-Dist: six (>=1.12.0)
Requires-Dist: pyserial (>=3.4)
Requires-Dist: paramiko (>=2.4.2)
Requires-Dist: requests (>=2.21.0)
Requires-Dist: pyOpenSSL (>=18.0.0)
